{
  "Yarmouth Port": {
    "town": "Yarmouth Port",
    "listings": "148",
    "coords": [
      "-70.23",
      "41.71"
    ]
  },
  "Worcester": {
    "town": "Worcester",
    "listings": "360",
    "coords": [
      "-71.81",
      "42.27"
    ]
  },
  "Woods Hole": {
    "town": "Woods Hole",
    "listings": "55",
    "coords": [
      "-70.67",
      "41.53"
    ]
  },
  "Woburn": {
    "town": "Woburn",
    "listings": "211",
    "coords": [
      "-71.15",
      "42.49"
    ]
  },
  "Winthrop": {
    "town": "Winthrop",
    "listings": "72",
    "coords": [
      "-70.97",
      "42.38"
    ]
  },
  "Winchester": {
    "town": "Winchester",
    "listings": "16",
    "coords": [
      "-71.15",
      "42.45"
    ]
  },
  "Winchendon": {
    "town": "Winchendon",
    "listings": "13",
    "coords": [
      "-72.04",
      "42.68"
    ]
  },
  "Wilmington": {
    "town": "Wilmington",
    "listings": "46",
    "coords": [
      "-71.17",
      "42.56"
    ]
  },
  "Williamstown": {
    "town": "Williamstown",
    "listings": "171",
    "coords": [
      "-73.2",
      "42.71"
    ]
  },
  "Williamsburg": {
    "town": "Williamsburg",
    "listings": "37",
    "coords": [
      "-72.7567",
      "42.4134"
    ]
  },
  "Westport": {
    "town": "Westport",
    "listings": "88",
    "coords": [
      "-71.09",
      "41.65"
    ]
  },
  "Westport Point": {
    "town": "Westport Point",
    "listings": "16",
    "coords": [
      "-71.0815",
      "41.5704"
    ]
  },
  "Weston": {
    "town": "Weston",
    "listings": "15",
    "coords": [
      "-71.3034",
      "42.3662"
    ]
  },
  "Westminster": {
    "town": "Westminster",
    "listings": "18",
    "coords": [
      "-71.9101",
      "42.5454"
    ]
  },
  "Westford": {
    "town": "Westford",
    "listings": "17",
    "coords": [
      "-71.4378",
      "42.5791"
    ]
  },
  "Westfield": {
    "town": "Westfield",
    "listings": "58",
    "coords": [
      "-72.76",
      "42.14"
    ]
  },
  "Westborough": {
    "town": "Westborough",
    "listings": "62",
    "coords": [
      "-71.62",
      "42.27"
    ]
  },
  "West Yarmouth": {
    "town": "West Yarmouth",
    "listings": "422",
    "coords": [
      "-70.25",
      "41.65"
    ]
  },
  "West Wareham": {
    "town": "West Wareham",
    "listings": "20",
    "coords": [
      "-70.75",
      "41.79"
    ]
  },
  "West Tisbury": {
    "town": "West Tisbury",
    "listings": "201",
    "coords": [
      "-70.6700",
      "41.3938"
    ]
  },
  "West Stockbridge": {
    "town": "West Stockbridge",
    "listings": "62",
    "coords": [
      "-73.3664",
      "42.3366"
    ]
  },
  "West Roxbury": {
    "town": "West Roxbury",
    "listings": "71",
    "coords": [
      "-71.1497",
      "42.2793"
    ]
  },
  "West Newton": {
    "town": "West Newton",
    "listings": "27",
    "coords": [
      "-71.2085",
      "42.3529"
    ]
  },
  "West Hyannisport": {
    "town": "West Hyannisport",
    "listings": "26",
    "coords": [
      "-70.2984",
      "41.6407"
    ]
  },
  "West Harwich": {
    "town": "West Harwich",
    "listings": "122",
    "coords": [
      "-70.1212",
      "41.6618"
    ]
  },
  "West Dennis": {
    "town": "West Dennis",
    "listings": "213",
    "coords": [
      "-70.17",
      "41.67"
    ]
  },
  "West Chatham": {
    "town": "West Chatham",
    "listings": "63",
    "coords": [
      "-69.99",
      "41.68"
    ]
  },
  "West Brookfield": {
    "town": "West Brookfield",
    "listings": "13",
    "coords": [
      "-72.15",
      "42.24"
    ]
  },
  "West Barnstable": {
    "town": "West Barnstable",
    "listings": "49",
    "coords": [
      "-70.3657",
      "41.6956"
    ]
  },
  "Wellfleet": {
    "town": "Wellfleet",
    "listings": "469",
    "coords": [
      "-70.011",
      "41.9334"
    ]
  },
  "Wellesley": {
    "town": "Wellesley",
    "listings": "23",
    "coords": [
      "-71.29",
      "42.3"
    ]
  },
  "Wellesley Hills": {
    "town": "Wellesley Hills",
    "listings": "14",
    "coords": [
      "-71.2727",
      "42.3192"
    ]
  },
  "Webster": {
    "town": "Webster",
    "listings": "25",
    "coords": [
      "-71.87",
      "42.04"
    ]
  },
  "Wayland": {
    "town": "Wayland",
    "listings": "18",
    "coords": [
      "-71.3616",
      "42.3625"
    ]
  },
  "Watertown": {
    "town": "Watertown",
    "listings": "181",
    "coords": [
      "-71.18",
      "42.37"
    ]
  },
  "Wareham": {
    "town": "Wareham",
    "listings": "110",
    "coords": [
      "-70.72",
      "41.75"
    ]
  },
  "Ware": {
    "town": "Ware",
    "listings": "17",
    "coords": [
      "-72.25",
      "42.25"
    ]
  },
  "Waltham": {
    "town": "Waltham",
    "listings": "175",
    "coords": [
      "-71.24",
      "42.39"
    ]
  },
  "Wakefield": {
    "town": "Wakefield",
    "listings": "92",
    "coords": [
      "-71.07",
      "42.5"
    ]
  },
  "Vineyard Haven": {
    "town": "Vineyard Haven",
    "listings": "289",
    "coords": [
      "-70.6",
      "41.46"
    ]
  },
  "Truro": {
    "town": "Truro",
    "listings": "129",
    "coords": [
      "-70.0495",
      "41.997"
    ]
  },
  "Tewksbury": {
    "town": "Tewksbury",
    "listings": "22",
    "coords": [
      "-71.2342",
      "42.6106"
    ]
  },
  "Taunton": {
    "town": "Taunton",
    "listings": "47",
    "coords": [
      "-71.09",
      "41.9"
    ]
  },
  "Swansea": {
    "town": "Swansea",
    "listings": "11",
    "coords": [
      "-71.1898",
      "41.7482"
    ]
  },
  "Swampscott": {
    "town": "Swampscott",
    "listings": "53",
    "coords": [
      "-70.89",
      "42.47"
    ]
  },
  "Sturbridge": {
    "town": "Sturbridge",
    "listings": "18",
    "coords": [
      "-72.06",
      "42.1"
    ]
  },
  "Stoughton": {
    "town": "Stoughton",
    "listings": "29",
    "coords": [
      "-71.1045",
      "42.1245"
    ]
  },
  "Stoneham": {
    "town": "Stoneham",
    "listings": "32",
    "coords": [
      "-71.1",
      "42.47"
    ]
  },
  "Stockbridge": {
    "town": "Stockbridge",
    "listings": "73",
    "coords": [
      "-73.3201",
      "42.2808"
    ]
  },
  "Springfield": {
    "town": "Springfield",
    "listings": "224",
    "coords": [
      "-72.54",
      "42.12"
    ]
  },
  "Spencer": {
    "town": "Spencer",
    "listings": "15",
    "coords": [
      "-71.99",
      "42.25"
    ]
  },
  "Southwick": {
    "town": "Southwick",
    "listings": "41",
    "coords": [
      "-72.7702",
      "42.0541"
    ]
  },
  "Southfield": {
    "town": "Southfield",
    "listings": "27",
    "coords": [
      "-70.93",
      "42.15"
    ]
  },
  "Southborough": {
    "town": "Southborough",
    "listings": "14",
    "coords": [
      "-71.5256",
      "42.3056"
    ]
  },
  "South Yarmouth": {
    "town": "South Yarmouth",
    "listings": "444",
    "coords": [
      "-70.2",
      "41.67"
    ]
  },
  "South Wellfleet": {
    "town": "South Wellfleet",
    "listings": "77",
    "coords": [
      "-69.9793",
      "41.9056"
    ]
  },
  "South Lee": {
    "town": "South Lee",
    "listings": "14",
    "coords": [
      "-73.2486",
      "42.2875"
    ]
  },
  "South Hadley": {
    "town": "South Hadley",
    "listings": "23",
    "coords": [
      "-72.5747",
      "42.2596"
    ]
  },
  "South Egremont": {
    "town": "South Egremont",
    "listings": "33",
    "coords": [
      "-73.4411",
      "42.133"
    ]
  },
  "South Dennis": {
    "town": "South Dennis",
    "listings": "178",
    "coords": [
      "-70.15",
      "41.71"
    ]
  },
  "South Deerfield": {
    "town": "South Deerfield",
    "listings": "17",
    "coords": [
      "-72.59",
      "42.48"
    ]
  },
  "South Dartmouth": {
    "town": "South Dartmouth",
    "listings": "64",
    "coords": [
      "-70.961",
      "41.5742"
    ]
  },
  "South Chatham": {
    "town": "South Chatham",
    "listings": "182",
    "coords": [
      "-69.9875",
      "41.6888"
    ]
  },
  "Somerville": {
    "town": "Somerville",
    "listings": "561",
    "coords": [
      "-71.1",
      "42.39"
    ]
  },
  "Somerset": {
    "town": "Somerset",
    "listings": "30",
    "coords": [
      "-71.16",
      "41.74"
    ]
  },
  "Siasconset": {
    "town": "Siasconset",
    "listings": "106",
    "coords": [
      "-69.97",
      "41.26"
    ]
  },
  "Shrewsbury": {
    "town": "Shrewsbury",
    "listings": "52",
    "coords": [
      "-71.7387",
      "42.2945"
    ]
  },
  "Shelburne Falls": {
    "town": "Shelburne Falls",
    "listings": "60",
    "coords": [
      "-72.74",
      "42.61"
    ]
  },
  "Sheffield": {
    "town": "Sheffield",
    "listings": "61",
    "coords": [
      "-73.3555",
      "42.1089"
    ]
  },
  "Sharon": {
    "town": "Sharon",
    "listings": "53",
    "coords": [
      "-71.18",
      "42.12"
    ]
  },
  "Scituate": {
    "town": "Scituate",
    "listings": "161",
    "coords": [
      "-70.77",
      "42.21"
    ]
  },
  "Saugus": {
    "town": "Saugus",
    "listings": "34",
    "coords": [
      "-71.01",
      "42.47"
    ]
  },
  "Sandwich": {
    "town": "Sandwich",
    "listings": "227",
    "coords": [
      "-70.43",
      "41.74"
    ]
  },
  "Sandisfield": {
    "town": "Sandisfield",
    "listings": "31",
    "coords": [
      "-73.13",
      "42.1068"
    ]
  },
  "Salisbury": {
    "town": "Salisbury",
    "listings": "154",
    "coords": [
      "-70.84",
      "42.83"
    ]
  },
  "Salem": {
    "town": "Salem",
    "listings": "440",
    "coords": [
      "-70.85",
      "42.52"
    ]
  },
  "Sagamore Beach": {
    "town": "Sagamore Beach",
    "listings": "113",
    "coords": [
      "-70.5271",
      "41.8048"
    ]
  },
  "Rutland": {
    "town": "Rutland",
    "listings": "12",
    "coords": [
      "-71.96",
      "42.36"
    ]
  },
  "Roxbury": {
    "town": "Roxbury",
    "listings": "269",
    "coords": [
      "-71.0848",
      "42.3251"
    ]
  },
  "Roxbury Crossing": {
    "town": "Roxbury Crossing",
    "listings": "87",
    "coords": [
      "-71.0982",
      "42.3314"
    ]
  },
  "Rowley": {
    "town": "Rowley",
    "listings": "13",
    "coords": [
      "-70.87",
      "42.72"
    ]
  },
  "Roslindale": {
    "town": "Roslindale",
    "listings": "87",
    "coords": [
      "-71.1301",
      "42.2814"
    ]
  },
  "Rockport": {
    "town": "Rockport",
    "listings": "308",
    "coords": [
      "-70.62",
      "42.65"
    ]
  },
  "Richmond": {
    "town": "Richmond",
    "listings": "27",
    "coords": [
      "-73.3644",
      "42.3754"
    ]
  },
  "Revere": {
    "town": "Revere",
    "listings": "182",
    "coords": [
      "-70.99",
      "42.42"
    ]
  },
  "Rehoboth": {
    "town": "Rehoboth",
    "listings": "14",
    "coords": [
      "-71.2643",
      "41.8431"
    ]
  },
  "Randolph": {
    "town": "Randolph",
    "listings": "42",
    "coords": [
      "-71.05",
      "42.18"
    ]
  },
  "Quincy": {
    "town": "Quincy",
    "listings": "230",
    "coords": [
      "-71.01",
      "42.26"
    ]
  },
  "Provincetown": {
    "town": "Provincetown",
    "listings": "1,186",
    "coords": [
      "-70.18",
      "42.05"
    ]
  },
  "Pocasset": {
    "town": "Pocasset",
    "listings": "89",
    "coords": [
      "-70.64",
      "41.69"
    ]
  },
  "Plymouth": {
    "town": "Plymouth",
    "listings": "469",
    "coords": [
      "-70.68",
      "41.98"
    ]
  },
  "Pittsfield": {
    "town": "Pittsfield",
    "listings": "201",
    "coords": [
      "-73.26",
      "42.45"
    ]
  },
  "Peabody": {
    "town": "Peabody",
    "listings": "37",
    "coords": [
      "-70.97",
      "42.53"
    ]
  },
  "Palmer": {
    "town": "Palmer",
    "listings": "20",
    "coords": [
      "-72.31",
      "42.19"
    ]
  },
  "Otis": {
    "town": "Otis",
    "listings": "36",
    "coords": [
      "-73.0631",
      "42.1942"
    ]
  },
  "Osterville": {
    "town": "Osterville",
    "listings": "138",
    "coords": [
      "-70.3826",
      "41.6352"
    ]
  },
  "Orleans": {
    "town": "Orleans",
    "listings": "446",
    "coords": [
      "-70",
      "41.79"
    ]
  },
  "Orange": {
    "town": "Orange",
    "listings": "28",
    "coords": [
      "-72.3",
      "42.6"
    ]
  },
  "Onset": {
    "town": "Onset",
    "listings": "81",
    "coords": [
      "-70.67",
      "41.75"
    ]
  },
  "Oak Bluffs": {
    "town": "Oak Bluffs",
    "listings": "613",
    "coords": [
      "-70.5616",
      "41.4555"
    ]
  },
  "Norwood": {
    "town": "Norwood",
    "listings": "15",
    "coords": [
      "-71.19",
      "42.19"
    ]
  },
  "Northampton": {
    "town": "Northampton",
    "listings": "112",
    "coords": [
      "-72.67",
      "42.33"
    ]
  },
  "North Weymouth": {
    "town": "North Weymouth",
    "listings": "19",
    "coords": [
      "-70.9429",
      "42.2358"
    ]
  },
  "North Truro": {
    "town": "North Truro",
    "listings": "351",
    "coords": [
      "-70.0902",
      "42.0366"
    ]
  },
  "North Falmouth": {
    "town": "North Falmouth",
    "listings": "140",
    "coords": [
      "-70.63",
      "41.64"
    ]
  },
  "North Chatham": {
    "town": "North Chatham",
    "listings": "92",
    "coords": [
      "-69.96",
      "41.7023"
    ]
  },
  "North Andover": {
    "town": "North Andover",
    "listings": "57",
    "coords": [
      "-71.1351",
      "42.6982"
    ]
  },
  "North Adams": {
    "town": "North Adams",
    "listings": "149",
    "coords": [
      "-73.12",
      "42.68"
    ]
  },
  "Newtonville": {
    "town": "Newtonville",
    "listings": "45",
    "coords": [
      "-71.2081",
      "42.3494"
    ]
  },
  "Newton": {
    "town": "Newton",
    "listings": "63",
    "coords": [
      "-71.21",
      "42.33"
    ]
  },
  "Newton Highlands": {
    "town": "Newton Highlands",
    "listings": "36",
    "coords": [
      "-71.2071",
      "42.3224"
    ]
  },
  "Newton Center": {
    "town": "Newton Center",
    "listings": "47",
    "coords": [
      "-71.1948",
      "42.3248"
    ]
  },
  "Newburyport": {
    "town": "Newburyport",
    "listings": "175",
    "coords": [
      "-70.89",
      "42.81"
    ]
  },
  "Newbury": {
    "town": "Newbury",
    "listings": "116",
    "coords": [
      "-70.89",
      "42.81"
    ]
  },
  "New Bedford": {
    "town": "New Bedford",
    "listings": "76",
    "coords": [
      "-70.94",
      "41.66"
    ]
  },
  "Natick": {
    "town": "Natick",
    "listings": "23",
    "coords": [
      "-71.3492",
      "42.2814"
    ]
  },
  "Nantucket": {
    "town": "Nantucket",
    "listings": "1,220",
    "coords": [
      "-70.09",
      "41.27"
    ]
  },
  "Nahant": {
    "town": "Nahant",
    "listings": "45",
    "coords": [
      "-70.91",
      "42.41"
    ]
  },
  "Monterey": {
    "town": "Monterey",
    "listings": "62",
    "coords": [
      "-73.228",
      "42.1846"
    ]
  },
  "Montague": {
    "town": "Montague",
    "listings": "9",
    "coords": [
      "-72.53",
      "42.54"
    ]
  },
  "Milton": {
    "town": "Milton",
    "listings": "43",
    "coords": [
      "-71.08",
      "42.24"
    ]
  },
  "Millbury": {
    "town": "Millbury",
    "listings": "10",
    "coords": [
      "-71.7645",
      "42.191"
    ]
  },
  "Milford": {
    "town": "Milford",
    "listings": "49",
    "coords": [
      "-71.52",
      "42.15"
    ]
  },
  "Methuen": {
    "town": "Methuen",
    "listings": "24",
    "coords": [
      "-71.19",
      "42.73"
    ]
  },
  "Melrose": {
    "town": "Melrose",
    "listings": "60",
    "coords": [
      "-71.06",
      "42.46"
    ]
  },
  "Medford": {
    "town": "Medford",
    "listings": "247",
    "coords": [
      "-71.11",
      "42.42"
    ]
  },
  "Mattapoisett": {
    "town": "Mattapoisett",
    "listings": "57",
    "coords": [
      "-70.81",
      "41.67"
    ]
  },
  "Mattapan": {
    "town": "Mattapan",
    "listings": "67",
    "coords": [
      "-71.0914",
      "42.2771"
    ]
  },
  "Mashpee": {
    "town": "Mashpee",
    "listings": "475",
    "coords": [
      "-70.47",
      "41.61"
    ]
  },
  "Marstons Mills": {
    "town": "Marstons Mills",
    "listings": "69",
    "coords": [
      "-70.4179",
      "41.6583"
    ]
  },
  "Marshfield": {
    "town": "Marshfield",
    "listings": "130",
    "coords": [
      "-70.7",
      "42.09"
    ]
  },
  "Marlborough": {
    "town": "Marlborough",
    "listings": "50",
    "coords": [
      "-71.55",
      "42.35"
    ]
  },
  "Marion": {
    "town": "Marion",
    "listings": "50",
    "coords": [
      "-70.76",
      "41.7"
    ]
  },
  "Marblehead": {
    "town": "Marblehead",
    "listings": "210",
    "coords": [
      "-70.83",
      "42.49"
    ]
  },
  "Mansfield": {
    "town": "Mansfield",
    "listings": "20",
    "coords": [
      "-71.22",
      "42.02"
    ]
  },
  "Manchester": {
    "town": "Manchester",
    "listings": "43",
    "coords": [
      "-70.7674",
      "42.5664"
    ]
  },
  "Malden": {
    "town": "Malden",
    "listings": "192",
    "coords": [
      "-71.06",
      "42.43"
    ]
  },
  "Lynn": {
    "town": "Lynn",
    "listings": "103",
    "coords": [
      "-70.96",
      "42.47"
    ]
  },
  "Lowell": {
    "town": "Lowell",
    "listings": "98",
    "coords": [
      "-71.32",
      "42.64"
    ]
  },
  "Littleton": {
    "town": "Littleton",
    "listings": "23",
    "coords": [
      "-71.47",
      "42.54"
    ]
  },
  "Lexington": {
    "town": "Lexington",
    "listings": "50",
    "coords": [
      "-71.23",
      "42.45"
    ]
  },
  "Leominster": {
    "town": "Leominster",
    "listings": "20",
    "coords": [
      "-71.77",
      "42.52"
    ]
  },
  "Lenox": {
    "town": "Lenox",
    "listings": "222",
    "coords": [
      "-73.29",
      "42.36"
    ]
  },
  "Leicester": {
    "town": "Leicester",
    "listings": "20",
    "coords": [
      "-71.9097",
      "42.2432"
    ]
  },
  "Lee": {
    "town": "Lee",
    "listings": "160",
    "coords": [
      "-73.25",
      "42.31"
    ]
  },
  "Lawrence": {
    "town": "Lawrence",
    "listings": "41",
    "coords": [
      "-71.16",
      "42.7"
    ]
  },
  "Lanesboro": {
    "town": "Lanesboro",
    "listings": "220",
    "coords": [
      "-73.2487",
      "42.5141"
    ]
  },
  "Lakeville": {
    "town": "Lakeville",
    "listings": "18",
    "coords": [
      "-70.94",
      "41.86"
    ]
  },
  "Kingston": {
    "town": "Kingston",
    "listings": "23",
    "coords": [
      "-70.72",
      "42"
    ]
  },
  "Jamaica Plain": {
    "town": "Jamaica Plain",
    "listings": "202",
    "coords": [
      "-71.1151",
      "42.3097"
    ]
  },
  "Ipswich": {
    "town": "Ipswich",
    "listings": "76",
    "coords": [
      "-70.83",
      "42.68"
    ]
  },
  "Indian Orchard": {
    "town": "Indian Orchard",
    "listings": "13",
    "coords": [
      "-72.5119",
      "42.1343"
    ]
  },
  "Hyde Park": {
    "town": "Hyde Park",
    "listings": "55",
    "coords": [
      "-71.1241",
      "42.2565"
    ]
  },
  "Hyannis": {
    "town": "Hyannis",
    "listings": "415",
    "coords": [
      "-70.2957",
      "41.6325"
    ]
  },
  "Hyannis Port": {
    "town": "Hyannis Port",
    "listings": "23",
    "coords": [
      "-70.2957",
      "41.6325"
    ]
  },
  "Huntington": {
    "town": "Huntington",
    "listings": "25",
    "coords": [
      "-72.88",
      "42.24"
    ]
  },
  "Humarock": {
    "town": "Humarock",
    "listings": "51",
    "coords": [
      "-70.6594",
      "42.1406"
    ]
  },
  "Hull": {
    "town": "Hull",
    "listings": "86",
    "coords": [
      "-70.88",
      "42.31"
    ]
  },
  "Hubbardston": {
    "town": "Hubbardston",
    "listings": "24",
    "coords": [
      "-72.0045",
      "42.4782"
    ]
  },
  "Housatonic": {
    "town": "Housatonic",
    "listings": "42",
    "coords": [
      "-73.36",
      "42.25"
    ]
  },
  "Holyoke": {
    "town": "Holyoke",
    "listings": "45",
    "coords": [
      "-72.64",
      "42.21"
    ]
  },
  "Holland": {
    "town": "Holland",
    "listings": "26",
    "coords": [
      "-72.15",
      "42.05"
    ]
  },
  "Hinsdale": {
    "town": "Hinsdale",
    "listings": "26",
    "coords": [
      "-73.1166",
      "42.4185"
    ]
  },
  "Hingham": {
    "town": "Hingham",
    "listings": "16",
    "coords": [
      "-70.89",
      "42.24"
    ]
  },
  "Haverhill": {
    "town": "Haverhill",
    "listings": "39",
    "coords": [
      "-71.09",
      "42.78"
    ]
  },
  "Harwich": {
    "town": "Harwich",
    "listings": "301",
    "coords": [
      "-70.03",
      "41.71"
    ]
  },
  "Harwich Port": {
    "town": "Harwich Port",
    "listings": "238",
    "coords": [
      "-70.06",
      "41.67"
    ]
  },
  "Hadley": {
    "town": "Hadley",
    "listings": "23",
    "coords": [
      "-72.5747",
      "42.2596"
    ]
  },
  "Groton": {
    "town": "Groton",
    "listings": "22",
    "coords": [
      "-71.57",
      "42.61"
    ]
  },
  "Greenfield": {
    "town": "Greenfield",
    "listings": "29",
    "coords": [
      "-72.6",
      "42.61"
    ]
  },
  "Great Barrington": {
    "town": "Great Barrington",
    "listings": "342",
    "coords": [
      "-73.36",
      "42.19"
    ]
  },
  "Granville": {
    "town": "Granville",
    "listings": "16",
    "coords": [
      "-72.925",
      "42.0853"
    ]
  },
  "Granby": {
    "town": "Granby",
    "listings": "16",
    "coords": [
      "-72.52",
      "42.26"
    ]
  },
  "Gloucester": {
    "town": "Gloucester",
    "listings": "397",
    "coords": [
      "-70.68",
      "42.63"
    ]
  },
  "Franklin": {
    "town": "Franklin",
    "listings": "54",
    "coords": [
      "-71.41",
      "42.09"
    ]
  },
  "Framingham": {
    "town": "Framingham",
    "listings": "78",
    "coords": [
      "-71.44",
      "42.31"
    ]
  },
  "Foxboro": {
    "town": "Foxboro",
    "listings": "144",
    "coords": [
      "-71.25",
      "42.06"
    ]
  },
  "Forestdale": {
    "town": "Forestdale",
    "listings": "19",
    "coords": [
      "-70.51",
      "41.68"
    ]
  },
  "Florence": {
    "town": "Florence",
    "listings": "59",
    "coords": [
      "-72.6758",
      "42.33"
    ]
  },
  "Fitchburg": {
    "town": "Fitchburg",
    "listings": "32",
    "coords": [
      "-71.82",
      "42.59"
    ]
  },
  "Falmouth": {
    "town": "Falmouth",
    "listings": "352",
    "coords": [
      "-70.56",
      "41.57"
    ]
  },
  "Fall River": {
    "town": "Fall River",
    "listings": "44",
    "coords": [
      "-71.1",
      "41.71"
    ]
  },
  "Fairhaven": {
    "town": "Fairhaven",
    "listings": "82",
    "coords": [
      "-70.9036",
      "41.6376"
    ]
  },
  "Everett": {
    "town": "Everett",
    "listings": "180",
    "coords": [
      "-71.05",
      "42.41"
    ]
  },
  "Essex": {
    "town": "Essex",
    "listings": "35",
    "coords": [
      "-70.77",
      "42.63"
    ]
  },
  "Edgartown": {
    "town": "Edgartown",
    "listings": "617",
    "coords": [
      "-70.5133",
      "41.3895"
    ]
  },
  "Easthampton": {
    "town": "Easthampton",
    "listings": "41",
    "coords": [
      "-72.67",
      "42.27"
    ]
  },
  "Eastham": {
    "town": "Eastham",
    "listings": "633",
    "coords": [
      "-72.67",
      "42.27"
    ]
  },
  "East Wareham": {
    "town": "East Wareham",
    "listings": "27",
    "coords": [
      "-70.649",
      "41.761"
    ]
  },
  "East Sandwich": {
    "town": "East Sandwich",
    "listings": "290",
    "coords": [
      "-70.43",
      "41.74"
    ]
  },
  "East Otis": {
    "town": "East Otis",
    "listings": "40",
    "coords": [
      "-73.0224",
      "42.1782"
    ]
  },
  "East Orleans": {
    "town": "East Orleans",
    "listings": "62",
    "coords": [
      "-69.9871",
      "41.7921"
    ]
  },
  "East Falmouth": {
    "town": "East Falmouth",
    "listings": "496",
    "coords": [
      "-70.56",
      "41.57"
    ]
  },
  "East Dennis": {
    "town": "East Dennis",
    "listings": "49",
    "coords": [
      "-70.16",
      "41.74"
    ]
  },
  "Duxbury": {
    "town": "Duxbury",
    "listings": "36",
    "coords": [
      "-70.67",
      "42.04"
    ]
  },
  "Dracut": {
    "town": "Dracut",
    "listings": "48",
    "coords": [
      "-71.3021",
      "42.6706"
    ]
  },
  "Dorchester": {
    "town": "Dorchester",
    "listings": "543",
    "coords": [
      "-71.0676",
      "42.3016"
    ]
  },
  "Dorchester Center": {
    "town": "Dorchester Center",
    "listings": "171",
    "coords": [
      "-71.0676",
      "42.3016"
    ]
  },
  "Dennis": {
    "town": "Dennis",
    "listings": "202",
    "coords": [
      "-70.2",
      "41.73"
    ]
  },
  "Dennis Port": {
    "town": "Dennis Port",
    "listings": "715",
    "coords": [
      "-70.14",
      "41.67"
    ]
  },
  "Dedham": {
    "town": "Dedham",
    "listings": "46",
    "coords": [
      "-71.18",
      "42.25"
    ]
  },
  "Danvers": {
    "town": "Danvers",
    "listings": "44",
    "coords": [
      "-70.95",
      "42.57"
    ]
  },
  "Dalton": {
    "town": "Dalton",
    "listings": "15",
    "coords": [
      "-73.1675",
      "42.4753"
    ]
  },
  "Cummington": {
    "town": "Cummington",
    "listings": "15",
    "coords": [
      "-72.9059",
      "42.4485"
    ]
  },
  "Cotuit": {
    "town": "Cotuit",
    "listings": "89",
    "coords": [
      "-70.435",
      "41.6244"
    ]
  },
  "Concord": {
    "town": "Concord",
    "listings": "24",
    "coords": [
      "-71.4",
      "42.45"
    ]
  },
  "Cohasset": {
    "town": "Cohasset",
    "listings": "30",
    "coords": [
      "-70.801",
      "42.2409"
    ]
  },
  "Chilmark": {
    "town": "Chilmark",
    "listings": "198",
    "coords": [
      "-70.7362",
      "41.3542"
    ]
  },
  "Chicopee": {
    "town": "Chicopee",
    "listings": "32",
    "coords": [
      "-72.57",
      "42.18"
    ]
  },
  "Chestnut Hill": {
    "town": "Chestnut Hill",
    "listings": "32",
    "coords": [
      "-71.1627",
      "42.3264"
    ]
  },
  "Cheshire": {
    "town": "Cheshire",
    "listings": "17",
    "coords": [
      "-73.16",
      "42.56"
    ]
  },
  "Chelsea": {
    "town": "Chelsea",
    "listings": "116",
    "coords": [
      "-71.03",
      "42.4"
    ]
  },
  "Chelmsford": {
    "town": "Chelmsford",
    "listings": "72",
    "coords": [
      "-71.3673",
      "42.5998"
    ]
  },
  "Chatham": {
    "town": "Chatham",
    "listings": "526",
    "coords": [
      "-69.96",
      "41.68"
    ]
  },
  "Charlestown": {
    "town": "Charlestown",
    "listings": "87",
    "coords": [
      "-71.062",
      "42.3779"
    ]
  },
  "Charlemont": {
    "town": "Charlemont",
    "listings": "38",
    "coords": [
      "-72.8732",
      "42.6241"
    ]
  },
  "Centerville": {
    "town": "Centerville",
    "listings": "300",
    "coords": [
      "-70.354",
      "41.6456"
    ]
  },
  "Cataumet": {
    "town": "Cataumet",
    "listings": "20",
    "coords": [
      "-70.5972",
      "41.6502"
    ]
  },
  "Canton": {
    "town": "Canton",
    "listings": "22",
    "coords": [
      "-71.1448",
      "42.1584"
    ]
  },
  "Cambridge": {
    "town": "Cambridge",
    "listings": "1,249",
    "coords": [
      "-71.12",
      "42.38"
    ]
  },
  "Buzzards Bay": {
    "town": "Buzzards Bay",
    "listings": "174",
    "coords": [
      "-70.61",
      "41.76"
    ]
  },
  "Burlington": {
    "town": "Burlington",
    "listings": "149",
    "coords": [
      "-71.2",
      "42.5"
    ]
  },
  "Brookline": {
    "town": "Brookline",
    "listings": "393",
    "coords": [
      "-71.14",
      "42.32"
    ]
  },
  "Brockton": {
    "town": "Brockton",
    "listings": "72",
    "coords": [
      "-71.02",
      "42.08"
    ]
  },
  "Brimfield": {
    "town": "Brimfield",
    "listings": "23",
    "coords": [
      "-72.2025",
      "42.116"
    ]
  },
  "Brighton": {
    "town": "Brighton",
    "listings": "356",
    "coords": [
      "-71.137",
      "42.3496"
    ]
  },
  "Brewster": {
    "town": "Brewster",
    "listings": "618",
    "coords": [
      "-70.08",
      "41.76"
    ]
  },
  "Braintree": {
    "town": "Braintree",
    "listings": "43",
    "coords": [
      "-71",
      "42.2"
    ]
  },
  "Boston": {
    "town": "Boston",
    "listings": "3,095",
    "coords": [
      "-71.02",
      "42.33"
    ]
  },
  "Billerica": {
    "town": "Billerica",
    "listings": "16",
    "coords": [
      "-71.2689",
      "42.5584"
    ]
  },
  "Beverly": {
    "town": "Beverly",
    "listings": "121",
    "coords": [
      "-70.84",
      "42.56"
    ]
  },
  "Belmont": {
    "town": "Belmont",
    "listings": "39",
    "coords": [
      "-71.18",
      "42.4"
    ]
  },
  "Belchertown": {
    "town": "Belchertown",
    "listings": "26",
    "coords": [
      "-72.41",
      "42.27"
    ]
  },
  "Bedford": {
    "town": "Bedford",
    "listings": "14",
    "coords": [
      "-70.94",
      "41.66"
    ]
  },
  "Becket": {
    "town": "Becket",
    "listings": "98",
    "coords": [
      "-73.1224",
      "42.3296"
    ]
  },
  "Barnstable": {
    "town": "Barnstable",
    "listings": "81",
    "coords": [
      "-70.36",
      "41.67"
    ]
  },
  "Attleboro": {
    "town": "Attleboro",
    "listings": "39",
    "coords": [
      "-71.29",
      "41.93"
    ]
  },
  "Athol": {
    "town": "Athol",
    "listings": "25",
    "coords": [
      "-72.23",
      "42.59"
    ]
  },
  "Ashfield": {
    "town": "Ashfield",
    "listings": "21",
    "coords": [
      "-72.8114",
      "42.5174"
    ]
  },
  "Ashburnham": {
    "town": "Ashburnham",
    "listings": "19",
    "coords": [
      "-71.94",
      "42.61"
    ]
  },
  "Arlington": {
    "town": "Arlington",
    "listings": "116",
    "coords": [
      "-71.16",
      "42.42"
    ]
  },
  "Andover": {
    "town": "Andover",
    "listings": "69",
    "coords": [
      "-71.14",
      "42.66"
    ]
  },
  "Amherst": {
    "town": "Amherst",
    "listings": "126",
    "coords": [
      "-72.52",
      "42.38"
    ]
  },
  "Amesbury": {
    "town": "Amesbury",
    "listings": "18",
    "coords": [
      "-70.94",
      "42.85"
    ]
  },
  "Allston": {
    "town": "Allston",
    "listings": "177",
    "coords": [
      "-71.1321",
      "42.3554"
    ]
  },
  "Adams": {
    "town": "Adams",
    "listings": "38",
    "coords": [
      "-73.12",
      "42.63"
    ]
  },
  "Acton": {
    "town": "Acton",
    "listings": "33",
    "coords": [
      "-71.4328",
      "42.4851"
    ]
  },
  "Abington": {
    "town": "Abington",
    "listings": "18",
    "coords": [
      "-70.96",
      "42.12"
    ]
  }
}